genpac/__init__.py
genpac/__main__.py
genpac/config.py
genpac/core.py
genpac/template.py
genpac/util.py
genpac/format/__init__.py
genpac/format/base.py
genpac/format/copy.py
genpac/format/deprecated.py
genpac/format/dnsmasq.py
genpac/format/ip.py
genpac/format/list.py
genpac/format/pac.py
genpac/format/quantumult_x.py
genpac/format/shadowrocket.py
genpac/format/shadowsocks_acl.py
genpac/format/surge.py
genpac/format/v2ray.py
genpac/res/rule-syntax.txt
genpac/res/tpl-config.ini
genpac/res/tpl-pac-precise.js
genpac/res/tpl-pac-precise.min.js
genpac/res/tpl-pac.js
genpac/res/tpl-pac.min.js
genpac/res/tpl-user-rules.txt
genpac/server/__init__.py
genpac/server/build.py
genpac/server/core.py
genpac/server/view.py
genpac/server/static/jquery-3.6.1.min.js
genpac/server/static/style.css
genpac/server/templates/base.html
genpac/server/templates/index.html
genpac/server/templates/rules.html
genpac-3.0.1.dist-info/LICENSE
genpac-3.0.1.dist-info/METADATA
genpac-3.0.1.dist-info/WHEEL
genpac-3.0.1.dist-info/entry_points.txt
genpac-3.0.1.dist-info/top_level.txt
genpac-3.0.1.dist-info/RECORD
