Metadata-Version: 2.1
Name: genpac
Version: 3.0.1
Summary: convert gfwlist to pac or other formats, support custom rules.
Author-email: JinnLynn <eatfishlin@gmail.com>
License: MIT
Project-URL: Homepage, https://github.com/JinnLynn/genpac
Classifier: Topic :: Utilities
Classifier: License :: OSI Approved :: MIT License
Classifier: Programming Language :: Python :: 3
Classifier: Programming Language :: Python :: 3.8
Classifier: Programming Language :: Python :: 3.9
Classifier: Programming Language :: Python :: 3.10
Classifier: Programming Language :: Python :: 3.11
Classifier: Programming Language :: Python :: 3.12
Requires-Python: >=3.8
License-File: LICENSE
Requires-Dist: requests[socks] ==2.31.0
Requires-Dist: publicsuffixlist
Requires-Dist: PyYAML ==6.0.1
Requires-Dist: netaddr ==1.3.0
Provides-Extra: dev
Requires-Dist: tox ==4.15.1 ; extra == 'dev'
Requires-Dist: flake8 ; extra == 'dev'
Requires-Dist: pytest ; extra == 'dev'
Requires-Dist: pytest-cov ; extra == 'dev'
Requires-Dist: pytest-randomly ; extra == 'dev'
Requires-Dist: pacparser ; extra == 'dev'
Provides-Extra: server
Requires-Dist: Werkzeug ==2.2.2 ; extra == 'server'
Requires-Dist: Flask ==2.2.2 ; extra == 'server'
Requires-Dist: Flask-APScheduler ==1.12.4 ; extra == 'server'
Requires-Dist: watchdog ==2.1.9 ; extra == 'server'
